textpipe/__init__.py
textpipe/doc.py
textpipe/operation.py
textpipe/pipeline.py
textpipe-0.1.2.dist-info/METADATA
textpipe-0.1.2.dist-info/RECORD
textpipe-0.1.2.dist-info/WHEEL
textpipe-0.1.2.dist-info/top_level.txt
