Metadata-Version: 2.1
Name: textpipe
Version: 0.1.2
Summary: textpipe: clean and extract metadata from text
Home-page: https://github.com/textpipe/textpipe
License: UNKNOWN
Platform: UNKNOWN
Classifier: Programming Language :: Python :: 3.6
Classifier: License :: OSI Approved :: MIT License
Classifier: Operating System :: OS Independent
Requires-Dist: beautifulsoup4 (~=4.6)
Requires-Dist: cld2-cffi (~=0.1)
Requires-Dist: spacy (~=2.0)
Requires-Dist: textacy (~=0.6)
